leanllm/__init__.py
leanllm/cli.py
leanllm/engine.py
leanllm/models/__init__.py
leanllm/models/base.py
leanllm/models/gpt2.py
leanllm-0.2.0.dist-info/METADATA
leanllm-0.2.0.dist-info/WHEEL
leanllm-0.2.0.dist-info/entry_points.txt
leanllm-0.2.0.dist-info/top_level.txt
leanllm-0.2.0.dist-info/RECORD
