Metadata-Version: 2.4
Name: leanllm
Version: 0.2.0
Summary: leanllm
Requires-Python: >=3.10
Requires-Dist: torch>=2.9.1
Requires-Dist: transformers>=4.57.3
